CHANGELOG.txt
LICENCE.txt
MANIFEST.in
README.txt
setup.py
joshbasiccalculator/__init__.py
joshbasiccalculator_0934.egg-info/PKG-INFO
joshbasiccalculator_0934.egg-info/SOURCES.txt
joshbasiccalculator_0934.egg-info/dependency_links.txt
joshbasiccalculator_0934.egg-info/top_level.txt